cbig_network_correspondence/__init__.py
cbig_network_correspondence/compute_overlap_with_atlases.py
cbig_network_correspondence/grab_data_info.py
cbig_network_correspondence/load_example.py
cbig_network_correspondence/py.typed
cbig_network_correspondence/visualize_overlap_lib.py
cbig_network_correspondence/visualize_report_lib.py
cbig_network_correspondence-0.3.1.dist-info/LICENCE
cbig_network_correspondence-0.3.1.dist-info/METADATA
cbig_network_correspondence-0.3.1.dist-info/WHEEL
cbig_network_correspondence-0.3.1.dist-info/RECORD
