Metadata-Version: 2.1
Name: cbig_network_correspondence
Version: 0.3.1
Summary: A toolbox for exploring network correspondence across atlases
Home-page: https://rubykong.github.io/cbig_network_correspondence
License: MIT
Author: Ruby Kong
Author-email: roo.cone@gmail.com
Requires-Python: >=3.9.19,<4.0
Classifier: Development Status :: 4 - Beta
Classifier: Intended Audience :: Developers
Classifier: License :: OSI Approved :: MIT License
Classifier: Operating System :: OS Independent
Classifier: Programming Language :: Python
Classifier: Programming Language :: Python :: 3
Classifier: Programming Language :: Python :: 3.10
Classifier: Programming Language :: Python :: 3.11
Classifier: Programming Language :: Python :: 3.12
Classifier: Programming Language :: Python :: 3.7
Classifier: Programming Language :: Python :: 3.8
Classifier: Programming Language :: Python :: 3.9
Classifier: Topic :: Software Development :: Libraries :: Python Modules
Classifier: Typing :: Typed
Requires-Dist: brainspace (==0.1.10)
Requires-Dist: certifi (==2024.6.2)
Requires-Dist: charset-normalizer (==3.3.2)
Requires-Dist: colorcet (==3.1.0)
Requires-Dist: contourpy (==1.2.1)
Requires-Dist: cycler (==0.12.1)
Requires-Dist: fonttools (==4.53.0)
Requires-Dist: gitdb (==4.0.11)
Requires-Dist: gitpython (==3.1.43)
Requires-Dist: idna (==3.7)
Requires-Dist: importlib-resources (==6.4.0)
Requires-Dist: joblib (==1.4.2)
Requires-Dist: kiwisolver (==1.4.5)
Requires-Dist: lxml (==5.2.2)
Requires-Dist: matplotlib (==3.9.0)
Requires-Dist: natsort (==8.4.0)
Requires-Dist: nibabel (==5.2.1)
Requires-Dist: nilearn (==0.10.4)
Requires-Dist: numpy (==1.26.4)
Requires-Dist: packaging (==24.1)
Requires-Dist: pandas (==2.2.2)
Requires-Dist: pillow (==10.3.0)
Requires-Dist: plottable (==0.1.5)
Requires-Dist: pyparsing (==3.1.2)
Requires-Dist: python-dateutil (==2.9.0.post0)
Requires-Dist: pytz (==2024.1)
Requires-Dist: regfusion (==0.1.0)
Requires-Dist: requests (==2.32.3)
Requires-Dist: scikit-learn (==1.5.0)
Requires-Dist: scipy (==1.13.1)
Requires-Dist: seaborn (==0.13.2)
Requires-Dist: smmap (==5.0.1)
Requires-Dist: threadpoolctl (==3.5.0)
Requires-Dist: tzdata (==2024.1)
Requires-Dist: urllib3 (==2.2.1)
Requires-Dist: vtk (==9.3.0)
Requires-Dist: zipp (==3.19.2)
Project-URL: Repository, https://github.com/rubykong/cbig_network_correspondence
